[
    {
        "id":1,
        "query":"Dziecięca pornografia"
    },
    {
        "id":2,
        "query":"Router za 700zł"
    },
    {
        "id":3,
        "query":"Studenci za mało płacą"
    },
    {
        "id":4,
        "query":"System amerykański jest lepszy"
    },
    {
        "id":5,
        "query":"Służba zdrowia jest w opłakanym stanie"
    },
    {
        "id":6,
        "query":"Mój brat architekt"
    },
    {
        "id":7,
        "query":"Jak ktoś nie ma wyobraźni to ja bardzo przepraszam"
    },
    {
        "id":8,
        "query":"Aktualizacje telefonów"
    },
    {
        "id":9,
        "query":"Za mało godzin w semestrze"
    }
]